xgrid/__init__.py
xgrid/lang/__init__.py
xgrid/lang/generator.py
xgrid/lang/operator.py
xgrid/lang/parser.py
xgrid/lang/ir/__init__.py
xgrid/lang/ir/expression.py
xgrid/lang/ir/statement.py
xgrid/lang/ir/visitor.py
xgrid/util/__init__.py
xgrid/util/console.py
xgrid/util/ffi.py
xgrid/util/init.py
xgrid/util/logging.py
xgrid/util/typing/__init__.py
xgrid/util/typing/annotation.py
xgrid/util/typing/reference.py
xgrid/util/typing/value.py
xgrid/xgrid/__init__.py
xgrid-0.0.5.dist-info/METADATA
xgrid-0.0.5.dist-info/WHEEL
xgrid-0.0.5.dist-info/licenses/LICENSE
xgrid-0.0.5.dist-info/RECORD
