Metadata-Version: 2.1
Name: xgrid
Version: 0.0.5
Summary: Domain-specific language for developing partial differential equation solvers
Project-URL: Homepage, https://github.com/yhl1219/xgrid
Project-URL: Bug Tracker, https://github.com/yhl1219/xgrid/issues
Author-email: yhl1219 <yhliu2000@outlook.com>
License-File: LICENSE
Classifier: License :: OSI Approved :: MIT License
Classifier: Programming Language :: Python :: 3
Classifier: Topic :: Scientific/Engineering
Classifier: Topic :: Software Development :: Code Generators
Requires-Python: >=3.10
